.gitignore
MANIFEST.in
README.rst
bootstrap.py
buildout.cfg
setup.py
collective/__init__.py
collective.js.oembed.egg-info/PKG-INFO
collective.js.oembed.egg-info/SOURCES.txt
collective.js.oembed.egg-info/dependency_links.txt
collective.js.oembed.egg-info/entry_points.txt
collective.js.oembed.egg-info/namespace_packages.txt
collective.js.oembed.egg-info/not-zip-safe
collective.js.oembed.egg-info/requires.txt
collective.js.oembed.egg-info/top_level.txt
collective/js/__init__.py
collective/js/oembed/__init__.py
collective/js/oembed/configure.zcml
collective/js/oembed/example.pt
collective/js/oembed/example.zcml
collective/js/oembed/interfaces.py
collective/js/oembed/profiles/default/browserlayer.xml
collective/js/oembed/profiles/default/cssregistry.xml
collective/js/oembed/profiles/default/jsregistry.xml
collective/js/oembed/profiles/default/metadata.xml
collective/js/oembed/resources/jquery.oembed.js
collective/js/oembed/resources/jquery.oembed.min.js
docs/HISTORY.txt