Metadata-Version: 1.0
Name: collective.js.oembed
Version: 1.0a
Summary: JQuery oembed plistred in the Plone resource registry
Home-page: https://github.com/collective/collective.js.oembed
Author: JeanMichel FRANCOIS aka toutpt
Author-email: toutpt@gmail.com
License: GPL
Platform: UNKNOWN
Classifier: Programming Language :: Python
Classifier: Framework :: Plone
Classifier: Framework :: Plone :: 4.0
Classifier: Framework :: Plone :: 4.1
